uk_fuel_prices_api/__init__.py
uk_fuel_prices_api/const.py
uk_fuel_prices_api-0.0.5.dist-info/METADATA
uk_fuel_prices_api-0.0.5.dist-info/WHEEL
uk_fuel_prices_api-0.0.5.dist-info/licenses/LICENCE
uk_fuel_prices_api-0.0.5.dist-info/RECORD
