Metadata-Version: 2.3
Name: uk_fuel_prices_api
Version: 0.0.5
Summary: Python API to access latest fuel prices in the UK
Project-URL: Homepage, https://github.com/gaco79/uk_fuel_prices_api
Project-URL: Issues, https://github.com/gaco79/uk_fuel_prices_api/issues
Author-email: Gareth Cooper <gareth@garethcooper.com>
License-File: LICENCE
Classifier: Development Status :: 3 - Alpha
Classifier: License :: OSI Approved :: GNU Lesser General Public License v3 (LGPLv3)
Classifier: Operating System :: OS Independent
Classifier: Programming Language :: Python :: 3
Requires-Python: >=3.10
Requires-Dist: aiohttp>=3.9.0
Requires-Dist: asyncio>=3.4.0
Requires-Dist: pandas>=2.1.0
